Metadata-Version: 2.1
Name: Donut3d
Version: 0.111
Summary: 3d ASCII Donut3d in python
Home-page: UNKNOWN
Author-email: Grigoriev.ilia1@yandex.ru
License: UNKNOWN
Platform: UNKNOWN
